Metadata-Version: 2.1
Name: eduarduino
Version: 0.0.19
Summary: Arduino Nano + pyFirmata
Home-page: https://github.com/techurbana/pynano
Author: Techurbana
Author-email: techurbana@gmail.com
License: MIT
Platform: UNKNOWN
Classifier: Programming Language :: Python :: 3
Classifier: License :: OSI Approved :: MIT License
Classifier: Operating System :: OS Independent
